amp/__init__.py
amp/cli.py
amp/client.py
amp/dashboard.py
amp/models.py
amp/server.py
amp/store.py
amp/core/llm.py
amp/core/providers.py
amp/core/storage.py
amp/static/dashboard.html
amp_memory-0.1.0.dist-info/METADATA
amp_memory-0.1.0.dist-info/WHEEL
amp_memory-0.1.0.dist-info/entry_points.txt
amp_memory-0.1.0.dist-info/licenses/LICENSE
amp_memory-0.1.0.dist-info/RECORD
