Metadata-Version: 2.4
Name: amp-memory
Version: 0.1.0
Summary: AMP: The Agent Memory Protocol - A local-first, MCP-native memory server.
Author-email: Akshay Aggarwal <akshay@example.com>
License: MIT
License-File: LICENSE
Requires-Python: >=3.10
Requires-Dist: fastapi>=0.100
Requires-Dist: fastembed>=0.3
Requires-Dist: google-generativeai>=0.8.5
Requires-Dist: jinja2>=3.0
Requires-Dist: mcp>=1.0.0
Requires-Dist: mem0ai>=1.0.1
Requires-Dist: numpy>=1.24.0
Requires-Dist: ollama>=0.6.1
Requires-Dist: pydantic>=2.0
Requires-Dist: requests>=2.31
Requires-Dist: sqlite-utils>=3.36
Requires-Dist: typer>=0.9.0
Requires-Dist: uvicorn>=0.20
